{
    "header": {
        "logo": "https://techsometimes.com/products/html/constimes/assets//img/logo/logo-1.svg",
        "topbar": {
            "mensagem": "Cuidando da sua saúde emocional com acolhimento e profissionalismo",
            "telefone": "(62) 5562982045122",
            "telefone_link": "625562982045122",
            "email": "contato@seudominio.com",
            "endereco": "Atendimento psicológico online em todo o Brasil",
            "social": [
                {
                    "icon": "my-icon icon-facebook",
                    "link": "#"
                },
                {
                    "icon": "my-icon icon-instagram",
                    "link": "#"
                },
                {
                    "icon": "my-icon icon-twitter",
                    "link": "#"
                },
                {
                    "icon": "my-icon icon-linkedin",
                    "link": "#"
                }
            ]
        },
        "menu": [
            {
                "titulo": "Início",
                "link": "index.html",
                "active": "active",
                "submenu": []
            },
            {
                "titulo": "Sobre Nós",
                "link": "#",
                "active": "",
                "submenu": [
                    {
                        "titulo": "Quem Somos",
                        "link": "about-us.html"
                    },
                    {
                        "titulo": "Nossa Abordagem",
                        "link": "about-us-rtl.html"
                    }
                ]
            },
            {
                "titulo": "Serviços",
                "link": "#",
                "active": "",
                "submenu": [
                    {
                        "titulo": "Psicoterapia Individual",
                        "link": "service.html"
                    },
                    {
                        "titulo": "Terapia de Casal",
                        "link": "service-details.html"
                    },
                    {
                        "titulo": "Atendimento Online",
                        "link": "service-rtl.html"
                    }
                ]
            },
            {
                "titulo": "Conteúdos",
                "link": "#",
                "active": "",
                "submenu": [
                    {
                        "titulo": "Artigos",
                        "link": "blog.html"
                    },
                    {
                        "titulo": "Saúde Emocional",
                        "link": "blog-details.html"
                    }
                ]
            },
            {
                "titulo": "Contato",
                "link": "#",
                "active": "",
                "submenu": [
                    {
                        "titulo": "Fale Conosco",
                        "link": "contact.html"
                    }
                ]
            }
        ],
        "botao": {
            "titulo": "Agendar Sessão",
            "link": "contact.html"
        }
    },
    "banner": {
        "background": "assets/img/banner/v1/banner-1.jpg",
        "subtitulo": "Cuidado emocional e bem-estar",
        "titulo": "Transforme sua saúde mental com acompanhamento psicológico",
        "descricao": "A psicoterapia ajuda no autoconhecimento, no equilíbrio emocional e no enfrentamento dos desafios da vida.",
        "botoes": [
            {
                "titulo": "Descubra Mais",
                "link": "#"
            },
            {
                "titulo": "Como Funciona",
                "link": "#"
            }
        ]
    },
    "sobre": {
        "imagem_principal": "https://techsometimes.com/products/html/constimes/assets/img/about-us/about-img.jpg",
        "imagem_play": "assets/img/about-us/play-round.png",
        "video": "https://youtu.be/jDLuJLoaA_g",
        "subtitulo": "SOBRE NÓS",
        "titulo": "Psicologia com escuta, ética e acolhimento",
        "itens": [
            {
                "icone": "icon-Outer-Lines-6",
                "titulo": "Atendimento Humanizado",
                "descricao": "Um espaço seguro para escuta ativa, empatia e desenvolvimento emocional.",
                "delay": "0s"
            },
            {
                "icone": "icon-Outer-Lines-5",
                "titulo": "Abordagem Científica",
                "descricao": "Práticas baseadas em evidências para promover saúde mental e qualidade de vida.",
                "delay": "0.4s"
            }
        ],
        "botao": {
            "titulo": "Saiba Mais",
            "link": "#"
        }
    },
    "servicos": {
        "subtitulo": "Nossos Serviços",
        "titulo": "Atendimento psicológico especializado",
        "items": [
            {
                "titulo": "Psicoterapia Individual",
                "descricao": "Acompanhamento psicológico focado no autoconhecimento e na saúde emocional.",
                "icone": "icon-Outer-Lines-4",
                "imagem": "https://techsometimes.com/products/html/constimes/assets/img/service/v1/card-img-1.jpg",
                "delay": "0.3s"
            },
            {
                "titulo": "Terapia de Casal",
                "descricao": "Fortalecimento da comunicação e dos vínculos afetivos.",
                "icone": "icon-Outer-Lines-3",
                "imagem": "https://techsometimes.com/products/html/constimes/assets/img/service/v1/card-img-2.jpg",
                "delay": "0.4s"
            },
            {
                "titulo": "Atendimento Online",
                "descricao": "Sessões online com a mesma qualidade, segurança e sigilo do presencial.",
                "icone": "icon-Outer-Lines-2",
                "imagem": "https://techsometimes.com/products/html/constimes/assets/img/service/v1/card-img-3.jpg",
                "delay": "0.5s"
            }
        ]
    },
    "galeria": {
        "subtitulo": "Nossa Atuação",
        "titulo": "Apoiando Pessoas em Sua Jornada Emocional",
        "descricao": "Conheça alguns dos contextos e abordagens terapêuticas em que atuamos, sempre com foco no bem-estar emocional e na saúde mental.",
        "items": [
            {
                "classe_wrapper": "gallery-img-horizontal",
                "delay": "0.2s",
                "imagem": "https://techsometimes.com/products/html/constimes/assets/img/work-gallery/v1/card-img-1.jpg",
                "titulo": "Acompanhamento Terapêutico",
                "categoria": "Psicoterapia",
                "link": "project-details.html"
            },
            {
                "classe_wrapper": "gallery-img-vertical",
                "delay": "0.3s",
                "imagem": "https://techsometimes.com/products/html/constimes/assets/img/work-gallery/v1/card-img-2.jpg",
                "titulo": "Cuidado Emocional",
                "categoria": "Saúde Mental",
                "link": "project-details.html"
            },
            {
                "classe_wrapper": "gallery-img-vertical",
                "delay": "0.4s",
                "imagem": "https://techsometimes.com/products/html/constimes/assets/img/work-gallery/v1/card-img-3.jpg",
                "titulo": "Desenvolvimento Pessoal",
                "categoria": "Autoconhecimento",
                "link": "project-details.html"
            },
            {
                "classe_wrapper": "gallery-img-vertical",
                "delay": "0.2s",
                "imagem": "https://techsometimes.com/products/html/constimes/assets/img/work-gallery/v1/card-img-4.jpg",
                "titulo": "Bem-estar Emocional",
                "categoria": "Qualidade de Vida",
                "link": "project-details.html"
            },
            {
                "classe_wrapper": "gallery-img-vertical",
                "delay": "0.3s",
                "imagem": "https://techsometimes.com/products/html/constimes/assets/img/work-gallery/v1/card-img-5.jpg",
                "titulo": "Suporte Psicológico",
                "categoria": "Acolhimento",
                "link": "project-details.html"
            },
            {
                "classe_wrapper": "gallery-img-horizontal",
                "delay": "0.4s",
                "imagem": "https://techsometimes.com/products/html/constimes/assets/img/work-gallery/v1/card-img-6.jpg",
                "titulo": "Equilíbrio Emocional",
                "categoria": "Saúde Integral",
                "link": "project-details.html"
            }
        ]
    },
    "contadores": {
        "items": [
            {
                "icone": "my-icon icon-group-icon-8",
                "titulo": "Pacientes Acompanhados",
                "numero": 200,
                "sufixo": "+",
                "min": 15,
                "delay": "0.1s",
                "count_delay": 200
            },
            {
                "icone": "my-icon icon-group-icon-7",
                "titulo": "Especialistas Qualificados",
                "numero": 20,
                "sufixo": "+",
                "min": 1,
                "delay": "0.2s",
                "count_delay": 300
            },
            {
                "icone": "my-icon icon-group-icon-6",
                "titulo": "Atendimentos Realizados",
                "numero": 10,
                "sufixo": "k+",
                "min": 1,
                "delay": "0.3s",
                "count_delay": 400
            },
            {
                "icone": "my-icon icon-user-stars",
                "titulo": "Avaliações Positivas",
                "numero": 900,
                "sufixo": "+",
                "min": 1,
                "delay": "0.4s",
                "count_delay": 500
            }
        ]
    },
    "faq": {
        "subtitulo": "Dúvidas Frequentes",
        "titulo": "Esclarecendo Suas Principais Perguntas",
        "imagem": "https://techsometimes.com/products/html/constimes/assets/img/faq/profile-img.jpg",
        "items": [
            {
                "pergunta": "Como funciona o atendimento psicológico?",
                "resposta": "O atendimento psicológico ocorre por meio de sessões individuais, em um ambiente acolhedor e sigiloso, com foco nas suas necessidades emocionais."
            },
            {
                "pergunta": "Quando devo procurar um psicólogo?",
                "resposta": "Sempre que sentir dificuldades emocionais, ansiedade, estresse ou necessidade de autoconhecimento, o apoio psicológico pode ajudar."
            },
            {
                "pergunta": "O atendimento é presencial ou online?",
                "resposta": "Oferecemos atendimentos presenciais e online, garantindo flexibilidade e conforto para cada paciente."
            }
        ]
    },
    "processos": {
        "subtitulo": "Nosso Processo Terapêutico",
        "titulo": "Cuidando da Sua Saúde Emocional em Etapas Claras",
        "items": [
            {
                "icone": "my-icon icon-Outer-Lines-1",
                "ordem": "Etapa 01",
                "titulo": "Acolhimento Inicial",
                "descricao": "Primeiro contato focado em escuta ativa e compreensão das suas necessidades emocionais.",
                "delay": "0.1s"
            },
            {
                "icone": "my-icon icon-Outer-Lines-5",
                "ordem": "Etapa 02",
                "titulo": "Avaliação Psicológica",
                "descricao": "Análise cuidadosa do contexto emocional, comportamental e histórico do paciente.",
                "delay": "0.2s"
            },
            {
                "icone": "my-icon icon-group-icon-4",
                "ordem": "Etapa 03",
                "titulo": "Plano Terapêutico",
                "descricao": "Definição de estratégias personalizadas para promover equilíbrio emocional e bem-estar.",
                "delay": "0.3s"
            },
            {
                "icone": "my-icon icon-Outer-Lines",
                "ordem": "Etapa 04",
                "titulo": "Evolução Contínua",
                "descricao": "Acompanhamento constante para fortalecer o autoconhecimento e a saúde mental.",
                "delay": "0.4s"
            }
        ]
    },
    "depoimentos": {
        "subtitulo": "Depoimentos",
        "titulo": "Experiências Reais de Quem Buscou Apoio Psicológico",
        "items": [
            {
                "titulo": "Um espaço seguro para falar e evoluir",
                "texto": "O acompanhamento psicológico me ajudou a lidar melhor com a ansiedade e a compreender minhas emoções.",
                "estrelas": 5,
                "imagem": "https://techsometimes.com/products/html/constimes/assets/img/clients-review/v1/profile-1.png",
                "nome": "Mariana Silva",
                "cargo": "Paciente"
            },
            {
                "titulo": "Mudança significativa na minha qualidade de vida",
                "texto": "Com o apoio terapêutico, consegui desenvolver autoconfiança e melhorar meus relacionamentos.",
                "estrelas": 5,
                "imagem": "https://techsometimes.com/products/html/constimes/assets/img/clients-review/v1/profile-2.png",
                "nome": "Carlos Mendes",
                "cargo": "Paciente"
            },
            {
                "titulo": "Atendimento humano e profissional",
                "texto": "Me senti acolhida desde a primeira sessão. Um trabalho sério e extremamente cuidadoso.",
                "estrelas": 5,
                "imagem": "https://techsometimes.com/products/html/constimes/assets/img/clients-review/v1/profile-2.png",
                "nome": "Ana Paula Rocha",
                "cargo": "Paciente"
            }
        ]
    },
    "get_in_touch": {
        "titulo_principal": "Estratégias Terapêuticas para o Seu Bem-Estar",
        "descricao": "Atendimento psicológico focado em acolhimento, escuta ativa e desenvolvimento emocional para uma vida mais equilibrada.",
        "lista": [
            {
                "icone": "icon-chack-mark",
                "texto": "Abordagem terapêutica personalizada para cada paciente."
            },
            {
                "icone": "icon-chack-mark",
                "texto": "Acompanhamento contínuo do progresso emocional."
            },
            {
                "icone": "icon-chack-mark",
                "texto": "Atendimento ético, humano e baseado em evidências."
            }
        ],
        "botao": {
            "titulo": "Descubra Mais",
            "link": "#"
        },
        "contadores": [
            {
                "icone": "icon-Outline",
                "titulo": "Pacientes Atendidos",
                "min": 1,
                "max": 1700,
                "duracao": 1400,
                "delay": 300,
                "sufixo": "+"
            },
            {
                "icone": "icon-group-icon-3",
                "titulo": "Sessões Realizadas",
                "min": 1,
                "max": 2000,
                "duracao": 1400,
                "delay": 300,
                "sufixo": "+"
            }
        ],
        "formulario": {
            "subtitulo": "ENTRE EM CONTATO",
            "titulo": "Cuidado Psicológico Profissional",
            "action": "assets/mail.php",
            "placeholders": {
                "nome": "Seu Nome",
                "email": "Seu E-mail",
                "telefone": "Telefone",
                "mensagem": "Mensagem"
            },
            "botao": "Enviar Mensagem"
        }
    },
    "latest_news": {
        "subtitulo": "Conteúdos Recentes",
        "titulo": "Psicologia, Saúde Emocional e Autoconhecimento",
        "posts": [
            {
                "data": "11 janeiro, 2024",
                "imagem": "https://techsometimes.com/products/html/constimes/assets/img/news/v1/post-1.jpg",
                "titulo": "A importância da terapia no autocuidado emocional",
                "descricao": "Entenda como o acompanhamento psicológico contribui para o equilíbrio emocional e qualidade de vida.",
                "link": "blog-details.html",
                "botao": "Leia Mais"
            },
            {
                "data": "11 janeiro, 2024",
                "imagem": "https://techsometimes.com/products/html/constimes/assets/img/news/v1/post-2.jpg",
                "titulo": "Ansiedade: como identificar e tratar",
                "descricao": "Conheça os principais sinais da ansiedade e como a psicoterapia pode ajudar no tratamento.",
                "link": "blog-details.html",
                "botao": "Leia Mais"
            },
            {
                "data": "11 janeiro, 2024",
                "imagem": "https://techsometimes.com/products/html/constimes/assets/img/news/v1/post-3.jpg",
                "titulo": "Terapia online funciona?",
                "descricao": "Descubra os benefícios da terapia online e para quem ela é indicada.",
                "link": "blog-details.html",
                "botao": "Leia Mais"
            }
        ]
    },
    "footer": {
        "logo": {
            "imagem": "https://techsometimes.com/products/html/constimes/assets/img/logo/logo-2.svg",
            "link": "index.html"
        },
        "descricao": "Espaço dedicado ao cuidado psicológico, promovendo saúde emocional, autoconhecimento e bem-estar por meio de atendimentos éticos e humanizados.",
        "redes_sociais": [
            {
                "icone": "icon-facebook",
                "link": "#"
            },
            {
                "icone": "icon-twitter",
                "link": "#"
            },
            {
                "icone": "icon-instagram",
                "link": "#"
            },
            {
                "icone": "icon-pinterest",
                "link": "#"
            }
        ],
        "newsletter": {
            "action": "#",
            "placeholder": "Seu endereço de e-mail"
        },
        "posts_populares": {
            "titulo": "Conteúdos Populares",
            "items": [
                {
                    "imagem": "https://techsometimes.com/products/html/constimes/assets/img/footer-img/post-1.jpg",
                    "titulo": "Como a psicoterapia ajuda no equilíbrio emocional",
                    "data": "20 de outubro, 2024",
                    "link": "#"
                },
                {
                    "imagem": "https://techsometimes.com/products/html/constimes/assets/img/footer-img/post-2.jpg",
                    "titulo": "Autoconhecimento como base da saúde mental",
                    "data": "20 de outubro, 2024",
                    "link": "#"
                }
            ]
        },
        "links_uteis": {
            "titulo": "Links Úteis",
            "items": [
                {
                    "titulo": "Psicoterapia Individual",
                    "link": "#"
                },
                {
                    "titulo": "Terapia de Casal",
                    "link": "#"
                },
                {
                    "titulo": "Atendimento Online",
                    "link": "#"
                },
                {
                    "titulo": "Desenvolvimento Emocional",
                    "link": "#"
                },
                {
                    "titulo": "Saúde Mental no Trabalho",
                    "link": "#"
                },
                {
                    "titulo": "Autocuidado",
                    "link": "#"
                }
            ]
        },
        "contato": {
            "titulo": "Fale Conosco",
            "items": [
                {
                    "icone": "icon-phone-book",
                    "label": "Telefone",
                    "valor": "(62) 5562982045122",
                    "link": "tel:5562982045122"
                },
                {
                    "icone": "icon-envelope-solid",
                    "label": "E-mail",
                    "valor": "contato@seudominio.com",
                    "link": "mailto:contato@seudominio.com"
                },
                {
                    "icone": "icon-location-pin-solid",
                    "label": "Localização",
                    "valor": "Atendimento presencial e online",
                    "link": "#"
                }
            ]
        },
        "copyright": {
            "texto": "© Constimes 2024 | Todos os direitos reservados",
            "links": [
                {
                    "titulo": "Termos & Condições",
                    "link": "#"
                },
                {
                    "titulo": "Política de Privacidade",
                    "link": "#"
                },
                {
                    "titulo": "Contato",
                    "link": "#"
                }
            ]
        }
    }
}